README.txt
setup.cfg
setup.py
xxxreport/__init__.py
xxxreport/main.py
xxxreport.egg-info/PKG-INFO
xxxreport.egg-info/SOURCES.txt
xxxreport.egg-info/dependency_links.txt
xxxreport.egg-info/entry_points.txt
xxxreport.egg-info/not-zip-safe
xxxreport.egg-info/top_level.txt