Metadata-Version: 1.0
Name: xxxreport
Version: 0.1.3
Summary: xxxreport tools extract all TODO/XXX ... comments in a python source source
Home-page: http://code.google.com/p/xxxreport/
Author: Stephane Klein
Author-email: stephane@harobed.org
License: GPL
Keywords: comments,extract,TODO
Platform: UNKNOWN
Classifier: Intended Audience :: Developers
Classifier: Development Status :: 4 - Beta
Classifier: License :: OSI Approved :: GNU General Public License (GPL)
Classifier: Natural Language :: English
Classifier: Operating System :: OS Independent
Classifier: Programming Language :: Python
Classifier: Topic :: Software Development :: Documentation
Classifier: Topic :: Terminals
